aloha_library/__init__.py
aloha_library/schemas/__init__.py
aloha_library/schemas/iam.py
aloha_library-0.1.0.dist-info/WHEEL
aloha_library-0.1.0.dist-info/METADATA
aloha_library-0.1.0.dist-info/RECORD
